{
  "_note": "هذا الملف يحتوي على الترجمة بالدارجة المغربية — يمكن تعديله يدوياً",
  "site": {
    "name": "نوفيل إسباس سيريغرافيك",
    "tagline": "طبّع هويّتك وعيشها بستايل",
    "description": "مستورد ومُوزّع رسمي لمستلزمات الطباعة النسيجية والسيريغرافيا والسوبليماسيون فالمغرب."
  },
  "nav": {
    "home": "الصفحة الرئيسية",
    "catalog": "الكتالوج",
    "categories": "الأقسام",
    "heatPresses": "مكابس الحرارة",
    "consumablesSeri": "مستهلكات السيريغرافيا",
    "consumablesSub": "مستهلكات السوبليماسيون",
    "printingMachines": "آلات الطباعة",
    "seriMachines": "آلات السيريغرافيا",
    "sublimables": "منتجات قابلة للسوبليماسيون",
    "promotions": "تخفيضات",
    "contact": "تواصل معنا",
    "quoteRequest": "طلب عرض أثمان",
    "search": "البحث...",
    "account": "حسابي",
    "cart": "السلة",
    "wishlist": "المفضلة"
  },
  "home": {
    "heroTitle": "مستلزمات احترافية للطباعة النسيجية",
    "heroSubtitle": "مستورد رسمي لـ Antex · Inknovator · Freesub · SEF Textile. كل اللي خاص الورشة ديالك.",
    "heroCtaPrimary": "استكشف الكتالوج",
    "heroCtaSecondary": "طلب عرض أثمان",
    "heroBadge": "مستورد رسمي فالمغرب",
    "featuredTitle": "المنتجات المميزة",
    "featuredSubtitle": "أكثر المنتجات طلبا من طرف المحترفين",
    "categoriesTitle": "أقسامنا",
    "categoriesSubtitle": "كامل المعدات لنشاطك في الطباعة",
    "kitsTitle": "كيتات البداية",
    "kitsSubtitle": "ابدأ أو وسّع ورشتك بباكجات جاهزة للاستعمال",
    "trustTitle": "علاش تختار نوفيل إسباس سيريغرافيك؟",
    "seeAll": "شوف كل المنتجات"
  },
  "catalog": {
    "products": "منتج",
    "showing": "عرض",
    "of": "من أصل",
    "sortDefault": "الترتيب الافتراضي",
    "sortPopular": "الأكثر مبيعا",
    "sortNewest": "الأحدث",
    "sortPriceAsc": "الثمن: من الأرخص",
    "sortPriceDesc": "الثمن: من الأغلى",
    "filters": "الفلاتر",
    "activeFilters": "فلاتر نشطة",
    "clearFilters": "مسح الكل",
    "applyFilters": "تطبيق",
    "inStock": "متوفر",
    "onSale": "تخفيض",
    "category": "القسم",
    "brand": "الماركة",
    "availability": "التوفر",
    "noProducts": "ما كاين حتى منتج.",
    "noProductsHint": "حاول تبدل الفلاتر أو البحث ديالك.",
    "loadMore": "حمّل أكثر"
  },
  "product": {
    "addToCart": "زيد للسلة",
    "askPrice": "اسأل على الثمن",
    "contactWhatsApp": "اطلب عبر واتساب",
    "quoteRequest": "طلب عرض أثمان مهني",
    "inStock": "متوفر",
    "outOfStock": "نفد المخزون",
    "onBackorder": "على الطلب",
    "lowStock": "كتاع الأخيرة",
    "description": "الوصف",
    "specifications": "المواصفات",
    "relatedProducts": "منتجات مكملة",
    "sku": "الرقم المرجعي",
    "categories": "الأقسام",
    "tags": "التصنيفات",
    "share": "شارك",
    "save": "احفظ",
    "selectVariant": "اختر نوع المنتج",
    "onSale": "تخفيض",
    "new": "جديد",
    "bestseller": "الأكثر مبيعا",
    "professional": "برو",
    "reviews": "تقييمات",
    "noReviews": "ما كاين حتى تقييم"
  },
  "trust": {
    "officialImporter": "مستورد رسمي",
    "officialImporterDesc": "Antex · Inknovator · Freesub",
    "fastDelivery": "توصيل 48 ساعة",
    "fastDeliveryDesc": "الدار البيضاء وكامل المغرب",
    "localStock": "مخزون محلي",
    "localStockDesc": "منتجات متوفرة على الفور",
    "whatsappSupport": "دعم واتساب",
    "whatsappSupportDesc": "رد في أقل من 5 دقائق",
    "returns": "استرجاع 14 يوم",
    "returnsDesc": "المنتجات الغير مفتوحة",
    "proInvoice": "فاتورة مهنية",
    "proInvoiceDesc": "TVA شامل · عرض أثمان متاح"
  },
  "contact": {
    "title": "تواصل معنا",
    "subtitle": "الفريق ديالنا متاح من الاثنين للسبت، 9 الصباح حتى 6 المسا",
    "phone": "الهاتف",
    "email": "الإيميل",
    "address": "العنوان",
    "whatsapp": "واتساب",
    "sendMessage": "ابعث رسالة",
    "name": "اسمك",
    "subject": "الموضوع",
    "message": "الرسالة",
    "send": "أرسل"
  },
  "footer": {
    "description": "مستورد ومُوزّع لمستلزمات السيريغرافيا والسوبليماسيون والطباعة النسيجية فالمغرب.",
    "quickLinks": "روابط سريعة",
    "categories": "الأقسام",
    "support": "الدعم",
    "rights": "جميع الحقوق محفوظة.",
    "madeIn": "صُنع بالمغرب",
    "faq": "أسئلة شائعة",
    "deliveryInfo": "التوصيل والاسترجاع",
    "terms": "الشروط العامة",
    "privacy": "الخصوصية",
    "about": "من نحن",
    "partners": "الماركات الشريكة"
  },
  "cta": {
    "whatsappFloat": "محتاج مساعدة؟",
    "whatsappResponse": "رد في 5 دقائق",
    "requestQuote": "عرض أثمان",
    "viewAll": "شوف الكل",
    "viewProduct": "شوف المنتج",
    "viewCategory": "استكشف القسم",
    "backToTop": "ارجع للفوق"
  },
  "pagination": {
    "previous": "السابق",
    "next": "التالي",
    "page": "صفحة"
  },
  "announcement": {
    "items": [
      "🚚 توصيل سريع لكامل المغرب",
      "📦 مستورد رسمي Antex & Inknovator",
      "💬 دعم واتساب متاح 7 أيام في الأسبوع",
      "💰 أثمان تنازلية من 5 وحدات",
      "🏭 مخزون متوفر في مستودعنا بالدار البيضاء"
    ]
  }
}
